vpsinfo/solusvm.py
vpsinfo/vpsinfo.py
vpsinfo-0.1.0.dist-info/METADATA
vpsinfo-0.1.0.dist-info/WHEEL
vpsinfo-0.1.0.dist-info/entry_points.txt
vpsinfo-0.1.0.dist-info/top_level.txt
vpsinfo-0.1.0.dist-info/RECORD
