Metadata-Version: 2.2
Name: vpsinfo
Version: 0.1.0
Summary: A CLI tool for monitoring VPS information using SolusVM API
Author-email: Keli Hu <dev@keli.hu>
License: MIT
Requires-Python: >=3.7
Requires-Dist: click
Requires-Dist: tabulate
Requires-Dist: requests
